test0017/__init__.py
test0017-2.0.dist-info/METADATA
test0017-2.0.dist-info/WHEEL
test0017-2.0.dist-info/top_level.txt
test0017-2.0.dist-info/RECORD
