Metadata-Version: 2.1
Name: test0017
Version: 2.0
Summary: Testing something
Home-page: UNKNOWN
Author: Tector Pro
License: UNKNOWN
Platform: UNKNOWN
Classifier: Development Status :: 5 - Production/Stable
Classifier: Intended Audience :: Education
Classifier: Operating System :: Microsoft :: Windows :: Windows 10
Classifier: License :: OSI Approved :: MIT License
Classifier: Programming Language :: Python :: 3
Requires-Dist: Abhi-pdf (==7.3)
